LICENSE
README.md
setup.py
uRAD.py
lib/__init__.py
lib/uRAD_firmware_lib.py
uRAD.egg-info/PKG-INFO
uRAD.egg-info/SOURCES.txt
uRAD.egg-info/dependency_links.txt
uRAD.egg-info/entry_points.txt
uRAD.egg-info/requires.txt
uRAD.egg-info/top_level.txt